{"start_url": "https://itviec.com/it-jobs", "domain": "itviec", "data_format": "json+ld", "schema": {"employmentType": "employmentType", "jobLocation_address_addressCountry": "jobLocation_address_addressCountry", "baseSalary_currency": "baseSalary_currency", "validThrough": "validThrough", "datePosted": "datePosted", "baseSalary_value_unitText": "baseSalary_unitText", "jobLocation_address_streetAddress": "jobLocation_address_addressLocality", "title": "title", "hiringOrganization_description": "description", "baseSalary_value_maxValue": "baseSalary_maxValue", "baseSalary_value_minValue": "baseSalary_minValue", "hiringOrganization_name": "hiringOrganization_name", "experienceRequirements": "experienceRequirements", "jobBenefits": "jobBenefits"}, "selectors": {"job_url": "//*[contains(@id, 'job_')]/div/div[2]/div[1]/div/h2/a", "next_page": "//*[@id='show_more']/a", "job_selectors": {"occupationalCategory": "/html[1]/body/div[3]/div/div/div", "skills": "/html[1]/body/div[1]/div[3]/div/div/div[2]/div[2]/div[4]/div/ul/li"}}, "is_finished": true}